account.py
authentication.py
base.py
market_data.py
streaming.py
tradier.py
trading.py
watchlist.py
tiny_tradier-0.0.1.dist-info/LICENSE
tiny_tradier-0.0.1.dist-info/METADATA
tiny_tradier-0.0.1.dist-info/WHEEL
tiny_tradier-0.0.1.dist-info/top_level.txt
tiny_tradier-0.0.1.dist-info/RECORD
