Metadata-Version: 2.1
Name: tiny_tradier
Version: 0.0.1
Summary: A simple Python wrapper for Tradier's Brokerage API
Author-email: Conner Brown <cobrobrown@gmail.com>
Project-URL: Homepage, https://github.com/cobrobrown/tiny_tradier
Classifier: Programming Language :: Python :: 3
Classifier: License :: OSI Approved :: MIT License
Classifier: Operating System :: OS Independent
Requires-Python: >=3.8
License-File: LICENSE
